odoo9_addon_web_dialog_size-9.0.1.0.0-py2.7-nspkg.pth
odoo_addons/web_dialog_size/__openerp__.py
odoo_addons/web_dialog_size/__init__.py
odoo_addons/web_dialog_size/README.rst
odoo_addons/web_dialog_size/view/qweb.xml
odoo_addons/web_dialog_size/static/description/icon.png
odoo_addons/web_dialog_size/static/src/js/web_dialog_size.js
odoo_addons/web_dialog_size/static/src/css/web_dialog_size.css
odoo_addons/web_dialog_size/static/src/xml/web_dialog_size.xml
odoo9_addon_web_dialog_size-9.0.1.0.0.dist-info/top_level.txt
odoo9_addon_web_dialog_size-9.0.1.0.0.dist-info/WHEEL
odoo9_addon_web_dialog_size-9.0.1.0.0.dist-info/RECORD
odoo9_addon_web_dialog_size-9.0.1.0.0.dist-info/metadata.json
odoo9_addon_web_dialog_size-9.0.1.0.0.dist-info/DESCRIPTION.rst
odoo9_addon_web_dialog_size-9.0.1.0.0.dist-info/METADATA
odoo9_addon_web_dialog_size-9.0.1.0.0.dist-info/namespace_packages.txt
